{"status":true,"page":1,"loadMore":true,"data_result":["dummy_data/graphics/cliparts/1.svg","dummy_data/graphics/cliparts/2.svg","dummy_data/graphics/cliparts/3.svg","dummy_data/graphics/cliparts/4.svg","dummy_data/graphics/cliparts/5.svg","dummy_data/graphics/cliparts/6.svg","dummy_data/graphics/cliparts/7.svg","dummy_data/graphics/cliparts/8.svg","dummy_data/graphics/cliparts/9.svg","dummy_data/graphics/cliparts/10.svg","dummy_data/graphics/cliparts/11.svg","dummy_data/graphics/cliparts/12.svg","dummy_data/graphics/cliparts/13.svg","dummy_data/graphics/cliparts/14.svg","dummy_data/graphics/cliparts/15.svg","dummy_data/graphics/cliparts/16.svg","dummy_data/graphics/cliparts/17.svg","dummy_data/graphics/cliparts/18.svg","dummy_data/graphics/cliparts/19.svg","dummy_data/graphics/cliparts/20.svg"],"message":"ClipArts Loaded."}